{
  "bundle_id": "ME_CH01",
  "questions": [
    {
      "id": "HS01",
      "subject": "機械製造",
      "unit": "第一章",
      "q": "下列何者屬於成形型加工機械？",
      "image_url": "",
      "options": ["車床", "放電加工機", "沖床", "珠擊機"],
      "a": 2,
      "reward": 15,
      "explanation": "成形型加工是在不增加或移除材料的情況下改變材料外形，例如沖床 [1, 2]。"
    },
    {
      "id": "HS02",
      "subject": "機械製造",
      "unit": "第一章",
      "q": "下列何者為最先進的製造工具機？",
      "image_url": "",
      "options": ["CNC車床", "自動螺絲機", "切削中心機", "車銑複合機"],
      "a": 3,
      "reward": 15,
      "explanation": "近年來更進一步將工具機複合化以提升效率，例如車銑複合機 [2, 3]。"
    },
    {
      "id": "HS03",
      "subject": "機械製造",
      "unit": "第一章",
      "q": "製造業是屬於第幾級產業？",
      "image_url": "",
      "options": ["大量生產", "中量生產", "第一級產業", "第二級產業"],
      "a": 3,
      "reward": 15,
      "explanation": "第二級產業包含將原料進行加工的製造業 [2, 4]。"
    },
    {
      "id": "HS04",
      "subject": "機械製造",
      "unit": "第一章",
      "q": "下列敘述何者不正確？",
      "image_url": "",
      "options": ["金融、保險屬於第二級產業", "採礦、煉鋼業是屬於第一級產業", "大量生產的年產量 100,000件以上", "鍛造機屬於成形型加工機械"],
      "a": 0,
      "reward": 15,
      "explanation": "金融與保險業屬於提供服務的第三級產業，而非第二級 [2, 4]。"
    },
    {
      "id": "HS05",
      "subject": "機械製造",
      "unit": "第一章",
      "q": "指出下列敘述何者不正確？",
      "image_url": "",
      "options": ["一般少量或零星工作使用普通工具機最適合", "彈性製造機只適合大量同一規格零件之製造", "未來刀具材料發展會朝向耐高溫、耐磨損方向發展", "任何產品之設計都要考慮成本的問題"],
      "a": 1,
      "reward": 15,
      "explanation": "彈性製造機主要用於中量生產，以應對變動的生產數量，而非僅限大量規格化生產 [2, 5]。"
    },
    {
      "id": "HS06",
      "subject": "機械製造",
      "unit": "第一章",
      "q": "下列何種零件的生產不適合用大量生產？",
      "image_url": "",
      "options": ["螺帽", "墊圈", "軸承", "書本印刷"],
      "a": 3,
      "reward": 15,
      "explanation": "螺栓、螺帽、軸承等規格化標準零件適合大量生產 [2, 5]。書本印刷雖屬第二級產業，但在機械製造分類脈絡中不屬此類 [2, 4]。"
    },
    {
      "id": "HS07",
      "subject": "機械製造",
      "unit": "第一章",
      "q": "下列何者屬於機械製造系統的輸入部分？",
      "image_url": "",
      "options": ["設計", "教育", "管理", "消耗品"],
      "a": 1,
      "reward": 15,
      "explanation": "輸入部分包含顧客需求、人力、材料、教育、能源及投資等 [2, 6]。"
    },
    {
      "id": "HS08",
      "subject": "機械製造",
      "unit": "第一章",
      "q": "下列何者不屬於製造成本？",
      "image_url": "",
      "options": ["人工費", "材料費", "機器折舊費", "銷售費"],
      "a": 3,
      "reward": 15,
      "explanation": "銷售費屬於銷售成本，包含推銷、廣告及運輸等費用，不屬於製造成本 [7, 8]。"
    },
    {
      "id": "HS09",
      "subject": "機械製造",
      "unit": "第一章",
      "q": "下列何者不屬於服務業？",
      "image_url": "",
      "options": ["大眾客運", "飯店餐飲", "機械製造", "倉儲物流"],
      "a": 2,
      "reward": 15,
      "explanation": "機械製造屬於第二級產業，而大眾客運、飯店及物流等屬於第三級服務業 [4, 8]。"
    },
    {
      "id": "HS10",
      "subject": "機械製造",
      "unit": "第一章",
      "q": "下列何者與機械製造的要求無關？",
      "image_url": "",
      "options": ["製品精度越高越好", "製造成本越低越好", "製造要考慮環保", "全程品質管制"],
      "a": 0,
      "reward": 15,
      "explanation": "製造精度應適合產品所需，過度設計與精度不足都不適當 [7, 8]。"
    },
    {
      "id": "HS11",
      "subject": "機械製造",
      "unit": "第一章",
      "q": "下列何者屬於傳統式切削加工法？",
      "image_url": "",
      "options": ["彎曲", "剪切", "滾磨", "拉削"],
      "a": 3,
      "reward": 15,
      "explanation": "拉削屬於傳統式切削性加工法之一 [8, 9]。"
    },
    {
      "id": "HS12",
      "subject": "機械製造",
      "unit": "第一章",
      "q": "下列何種加工法屬於非傳統式切削加工？",
      "image_url": "",
      "options": ["鑽床加工", "搪孔", "銑床加工", "電化加工"],
      "a": 3,
      "reward": 15,
      "explanation": "電化加工利用電能與化學作用達成切削，屬於非傳統式切削 [8, 10]。"
    },
    {
      "id": "HS13",
      "subject": "機械製造",
      "unit": "第一章",
      "q": "下列何種方法無法改變材料的機械性質？",
      "image_url": "",
      "options": ["磨削", "鍛造", "珠擊", "熱處理"],
      "a": 0,
      "reward": 15,
      "explanation": "磨削主要是移除材料的分割型加工，不以改變材料機械性質為主要目的 [1, 8, 11]。"
    },
    {
      "id": "HS14",
      "subject": "機械製造",
      "unit": "第一章",
      "q": "為減少切屑的損失，可用何種方法作初步成形？",
      "image_url": "",
      "options": ["車削", "磨削", "鑄造", "放電加工"],
      "a": 2,
      "reward": 15,
      "explanation": "無屑加工（如鑄造）可用於初步成形，能減少材料消耗與廢料產生 [8, 12, 13]。"
    },
    {
      "id": "HS15",
      "subject": "機械製造",
      "unit": "第一章",
      "q": "下列何者屬於表面層加工法？",
      "image_url": "",
      "options": ["電化研磨 (ECG)", "輪磨", "磁力成形", "拋光"],
      "a": 3,
      "reward": 15,
      "explanation": "拋光用於進一步精製產品表面，改善粗糙度並增加美觀 [8, 14]。"
    },
    {
      "id": "HS16",
      "subject": "機械製造",
      "unit": "第一章",
      "q": "滾軋加工是屬於哪一種加工法？",
      "image_url": "",
      "options": ["表面層加工", "傳統式切削法", "非傳統式切削法", "改變形狀的加工法"],
      "a": 3,
      "reward": 15,
      "explanation": "滾軋是以連續塑性變形的方式改變材料形狀，屬於無屑加工 [8, 12, 14]。"
    },
    {
      "id": "HS17",
      "subject": "機械製造",
      "unit": "第一章",
      "q": "下列何者不屬於無屑加工？",
      "image_url": "",
      "options": ["電積成形", "熱處理", "鍛造", "鑄造"],
      "a": 1,
      "reward": 15,
      "explanation": "熱處理屬於改變材料物理、機械或化學性質的加工法，不屬於改變形狀的無屑加工 [11, 15, 16]。"
    },
    {
      "id": "HS18",
      "subject": "機械製造",
      "unit": "第一章",
      "q": "欲切削灰鑄鐵及非鐵金屬工件，宜使用何種材質的刀具？",
      "image_url": "",
      "options": ["P類碳化物", "M類碳化物", "K類碳化物", "鑽石"],
      "a": 2,
      "reward": 15,
      "explanation": "K類碳化物刀具適用於灰鑄鐵、石頭及非鐵金屬的切削 [16, 17]。"
    },
    {
      "id": "HS19",
      "subject": "機械製造",
      "unit": "第一章",
      "q": "陶瓷刀具材料之主要成分為何？",
      "image_url": "",
      "options": ["氧化鋁", "碳化鎢", "鑽石", "氮化硼"],
      "a": 0,
      "reward": 15,
      "explanation": "陶瓷刀具是以氧化鋁 (Al2O3) 為主成分，加入結合劑壓製而成 [16, 18]。"
    },
    {
      "id": "HS20",
      "subject": "機械製造",
      "unit": "第一章",
      "q": "下列何種刀具材料可以最高之切削速度進行切削？",
      "image_url": "",
      "options": ["瓷金", "高速鋼", "碳鋼", "非鐵鑄合金"],
      "a": 0,
      "reward": 15,
      "explanation": "在選項中，瓷金的耐磨性與熱安定性高於高速鋼、碳鋼及非鐵鑄合金 [16, 19, 20]。"
    },
    {
      "id": "HS21",
      "subject": "機械製造",
      "unit": "第一章",
      "q": "陶瓷刀具不能應用在下列何種切削？",
      "image_url": "",
      "options": ["高溫切削", "振動切削", "高速切削", "精切削"],
      "a": 1,
      "reward": 15,
      "explanation": "陶瓷刀具脆性大，任何振動的情形都會造成刀口破裂，故不適合斷續或振動切削 [16, 19]。"
    },
    {
      "id": "HS22",
      "subject": "機械製造",
      "unit": "第一章",
      "q": "下列何者是高速鋼的組成元素？",
      "image_url": "",
      "options": ["Cr-Ni-Fe", "W-Cr-V-Fe", "Co-Cr-W-Fe", "W-Co-C-Fe"],
      "a": 1,
      "reward": 15,
      "explanation": "高速鋼 (HSS) 為鎢 (W)-鉻 (Cr)-釩 (V)-鐵 (Fe) 之多元合金 [16, 21]。"
    },
    {
      "id": "HS23",
      "subject": "機械製造",
      "unit": "第一章",
      "q": "18-4-1型鎢系高速鋼，其成分為鋼基中含有哪些元素？",
      "image_url": "",
      "options": ["鉻 18%、鎢 4%、釩 1%", "釩 18%、鉻 4%、鎢 1%", "釩 18%、鎢 4%、鉻 1%", "鎢 18%、鉻 4%、釩 1%"],
      "a": 3,
      "reward": 15,
      "explanation": "18-4-1 型意指鋼基材料中含有 18% 之鎢、4% 之鉻及 1% 之釩 [16, 22]。"
    },
    {
      "id": "HS24",
      "subject": "機械製造",
      "unit": "第一章",
      "q": "軸承鋼淬火之後，欲施以車削加工，宜選用何種車刀？",
      "image_url": "",
      "options": ["HSS", "碳化鎢", "鑽石", "CBN"],
      "a": 3,
      "reward": 15,
      "explanation": "立方晶氮化硼 (CBN) 極適合高硬度淬火鋼等難削材料的切削 [16, 19]。"
    },
    {
      "id": "HS25",
      "subject": "機械製造",
      "unit": "第一章",
      "q": "將 (1)鑽石 (2)陶瓷 (3)瓷金 (4)CBN (5)碳化鎢 依硬度由高而低排列，正確順序為何？",
      "image_url": "",
      "options": ["(1)(2)(3)(4)(5)", "(1)(3)(2)(4)(5)", "(1)(4)(2)(3)(5)", "(1)(4)(3)(2)(5)"],
      "a": 2,
      "reward": 15,
      "explanation": "硬度比率依序為：鑽石 > 立方晶氮化硼 (CBN) > 陶瓷 > 瓷金 > 碳化鎢 [20, 23]。"
    },
    {
      "id": "HS26",
      "subject": "機械製造",
      "unit": "第一章",
      "q": "材質為銅的光學鏡片需高精度鏡面加工時，應選用何種刀具材料效果最佳？",
      "image_url": "",
      "options": ["鑽石", "碳化鎢", "高碳鋼", "高速鋼"],
      "a": 0,
      "reward": 15,
      "explanation": "鑽石刀具適合用於鋁、銅等軟金屬，以獲取高精度及光亮如鏡的表面 [20, 23]。"
    },
    {
      "id": "HS27",
      "subject": "機械製造",
      "unit": "第一章",
      "q": "碳化鎢刀具約可耐多少度之高溫而不軟化？",
      "image_url": "",
      "options": ["200℃", "600℃", "820℃", "1,100℃"],
      "a": 3,
      "reward": 15,
      "explanation": "根據相關資料，碳化鎢之耐熱度約為 1,000 ～ 1,100℃ [17, 23, 24]。"
    },
    {
      "id": "HS28",
      "subject": "機械製造",
      "unit": "第一章",
      "q": "下列何者不是機械製造方法之趨勢？",
      "image_url": "",
      "options": ["加工方式趨向無屑加工及非傳統式切削", "材料使用趨向單一化，節省倉儲空間", "切削刀具趨向耐高溫及耐磨損", "加工設備趨向彈性化"],
      "a": 1,
      "reward": 15,
      "explanation": "現代趨勢是材料使用趨向多元化（如塑膠、陶瓷、複合材料），而非單一化 [23, 25]。"
    },
    {
      "id": "HS29",
      "subject": "機械製造",
      "unit": "第一章",
      "q": "切削硬度很高的材料，宜選用何種顏色塗層的碳化物刀具？",
      "image_url": "",
      "options": ["H類（灰色）", "S類（棕色）", "P類（藍色）", "N類（綠色）"],
      "a": 0,
      "reward": 15,
      "explanation": "塗成灰色的 H 類刀具專用於切削高硬度材料 [23, 24]。"
    },
    {
      "id": "HS30",
      "subject": "機械製造",
      "unit": "第一章",
      "q": "製造銼刀、鋸片，宜選用何種材料？",
      "image_url": "",
      "options": ["高速鋼", "高碳鋼", "碳化物", "陶瓷"],
      "a": 1,
      "reward": 15,
      "explanation": "高碳鋼 (HCS) 通常用於製造不要求耐高溫的手工具，如銼刀、鋸片及鏨子等 [21, 26]。"
    }
  ]
}