{
  "bundle_id": "MOCK_106_3_ME2",
  "questions": [
    {
      "id": "MOCK_106_3_ME2_001",
      "subject": "機械群專二",
      "unit": "106-3-四技二專-01機械群專二",
      "q": "若碳鋼桿件以車床車製梯形螺紋,考慮切削時的刀刃接觸長度大,車床主軸轉速低及車刀需預先依螺紋 角度研磨成形等因素,則應選用下列何種刀具材料最適合?",
      "image_url": "",
      "options": [
        "高碳鋼",
        "高速鋼",
        "陶瓷",
        "鑽石"
      ],
      "a": 1,
      "reward": 15,
      "explanation": "高速鋼韌性大,較適合低速及成形刀具使用 (D) 曲線板用於除圓弧外之弧線"
    },
    {
      "id": "MOCK_106_3_ME2_002",
      "subject": "機械群專二",
      "unit": "106-3-四技二專-01機械群專二",
      "q": "有關鐵金屬含碳量的敘述,下列何者不正確?",
      "image_url": "",
      "options": [
        "純鐵的含碳量 0.02% 以下",
        "碳鋼含碳量 0.02%~2.0%",
        "共析鋼含碳量 0.8%",
        "鑄鐵含碳量 6.67% 以上"
      ],
      "a": 3,
      "reward": 15,
      "explanation": "(D) 鑄鐵含碳量為 2.0%~6.67%"
    },
    {
      "id": "MOCK_106_3_ME2_003",
      "subject": "機械群專二",
      "unit": "106-3-四技二專-01機械群專二",
      "q": "下列鑄造法中,何者最符合「生產速度快、大量生產及鑄模可重複使用」的製造需求?",
      "image_url": "",
      "options": [
        "金屬模鑄造法",
        "陶瓷殼模法",
        "石膏模鑄造法",
        "砂模鑄造法"
      ],
      "a": 0,
      "reward": 15,
      "explanation": "正解：(A)；來源：106-3-四技二專-01機械群專二解析.pdf"
    },
    {
      "id": "MOCK_106_3_ME2_004",
      "subject": "機械群專二",
      "unit": "106-3-四技二專-01機械群專二",
      "q": "鑄造時需考慮到熱脹冷縮的物理特性,稱為收縮裕度。下列何者為收縮裕度主要的目的?",
      "image_url": "",
      "options": [
        "補償金屬液凝固前因溫度降低所產生的收縮",
        "補償金屬液凝固期間所產生的收縮",
        "補償金屬液凝固後溫度降低所產生的收縮",
        "補償砂模中之模穴空間因溫度降低所產生的收縮"
      ],
      "a": 2,
      "reward": 15,
      "explanation": "正解：(C)；來源：106-3-四技二專-01機械群專二解析.pdf"
    },
    {
      "id": "MOCK_106_3_ME2_005",
      "subject": "機械群專二",
      "unit": "106-3-四技二專-01機械群專二",
      "q": "下列何者為區分熱作加工與冷作加工的主要條件?",
      "image_url": "",
      "options": [
        "施作時工件的溫度",
        "採用的加工機種類",
        "加工時的施力大小",
        "製造成品的種類"
      ],
      "a": 0,
      "reward": 15,
      "explanation": "施作的溫度在工件的再結晶溫度以上為熱作加工;施"
    },
    {
      "id": "MOCK_106_3_ME2_006",
      "subject": "機械群專二",
      "unit": "106-3-四技二專-01機械群專二",
      "q": "有關各種銲接法之敘述,下列何者不正確?",
      "image_url": "",
      "options": [
        "潛弧銲接僅適合用於平銲",
        "電子束銲接僅適合於真空環境中操作",
        "衝擊銲接僅適合用於導電材料銲接",
        "發熱銲接僅適合用於現場可提供大電流的場合"
      ],
      "a": 3,
      "reward": 15,
      "explanation": "(D) 發熱銲接不需提供電源即可施作"
    },
    {
      "id": "MOCK_106_3_ME2_007",
      "subject": "機械群專二",
      "unit": "106-3-四技二專-01機械群專二",
      "q": "下列表面處理方法中,何者最適合用於海邊鹽份較多,銹蝕嚴重處之鐵材防腐蝕?",
      "image_url": "",
      "options": [
        "陽極氧化處理",
        "氮化法",
        "滲硼法",
        "鍍鋅處理"
      ],
      "a": 3,
      "reward": 15,
      "explanation": "(A) 陽極氧化處理適用於鋁合金表面處理 (B) 氮化法適用於鐵合金材料表面硬化 (C) 滲硼法適用於表面硬化  1"
    },
    {
      "id": "MOCK_106_3_ME2_008",
      "subject": "機械群專二",
      "unit": "106-3-四技二專-01機械群專二",
      "q": "在平板上使用長 100 mm 正弦桿檢測一錐度為 1: 5 的工件,若錐度製作正確,則量測結果正弦桿與平  1  1 板夾角應為幾度? ( tan 0.1  5.71 , tan 0.2  11.31  )",
      "image_url": "",
      "options": [
        "2.86°",
        "5.71°",
        "11.42°",
        "22.84°"
      ],
      "a": 2,
      "reward": 15,
      "explanation": "半錐角   tan 0.1  5.71 , 錐角  2   11.42  12"
    },
    {
      "id": "MOCK_106_3_ME2_009",
      "subject": "機械群專二",
      "unit": "106-3-四技二專-01機械群專二",
      "q": "有關各種加工母機進給量 (feed) 之敘述,下列何者正確?",
      "image_url": "",
      "options": [
        "車床以每分鐘車刀移動的距離 mm / min 表示",
        "銑床以每分鐘工件移動的距離 mm / min 表示",
        "鑽床以每分鐘鑽頭移動的距離 mm / min 表示",
        "鉋床以每分鐘工件移動的距離 mm / min 表示"
      ],
      "a": 1,
      "reward": 15,
      "explanation": "正解：(B)；來源：106-3-四技二專-01機械群專二解析.pdf"
    },
    {
      "id": "MOCK_106_3_ME2_010",
      "subject": "機械群專二",
      "unit": "106-3-四技二專-01機械群專二",
      "q": "以直徑 12 mm 端銑刀銑削中碳鋼材料,切削速度為 23 m / min,若依表 ( 一 ) 之檔位配置表,則應選用何 種檔位最適當? 表 ( 一 ) A B C D E L 73 121 200 325 508 H 591 982 1615 2622 3925",
      "image_url": "",
      "options": [
        "選用高速檔, A 檔位",
        "選用高速檔, B 檔位",
        "選用低速檔, C 檔位",
        "選用低速檔, E 檔位"
      ],
      "a": 0,
      "reward": 15,
      "explanation": "V    D N , 23    N 1000 N  610 rpm,故選用高速檔, A 檔位 第二部分:機械基礎實習"
    },
    {
      "id": "MOCK_106_3_ME2_011",
      "subject": "機械群專二",
      "unit": "106-3-四技二專-01機械群專二",
      "q": "研磨碳化鎢刀具材料之車刀,應選用何種磨粒之砂輪研磨最適當?",
      "image_url": "",
      "options": [
        "C",
        "GC",
        "A",
        "WA"
      ],
      "a": 1,
      "reward": 15,
      "explanation": "正解：(B)；來源：106-3-四技二專-01機械群專二解析.pdf"
    },
    {
      "id": "MOCK_106_3_ME2_012",
      "subject": "機械群專二",
      "unit": "106-3-四技二專-01機械群專二",
      "q": "車床上車削螺紋需使用中心規,下列何者不是中心規的功能?",
      "image_url": "",
      "options": [
        "檢查牙刀刀尖角度是否正確",
        "檢查車刀是否垂直工件",
        "檢查螺距是否正確",
        "檢查切削深度是否正確"
      ],
      "a": 3,
      "reward": 15,
      "explanation": "正解：(D)；來源：106-3-四技二專-01機械群專二解析.pdf"
    },
    {
      "id": "MOCK_106_3_ME2_013",
      "subject": "機械群專二",
      "unit": "106-3-四技二專-01機械群專二",
      "q": "將粉末冶金製程與鑄造製程相比較,下列何者為粉末冶金製程所獨有的特性?",
      "image_url": "",
      "options": [
        "可製造出特定孔隙率的產品",
        "適合大量生產",
        "屬於無屑加工,可節省材料",
        "可生產金屬純度高的產品 第二部分:機械基礎實習"
      ],
      "a": 0,
      "reward": 15,
      "explanation": "正解：(A)；來源：106-3-四技二專-01機械群專二解析.pdf"
    },
    {
      "id": "MOCK_106_3_ME2_014",
      "subject": "機械群專二",
      "unit": "106-3-四技二專-01機械群專二",
      "q": "有關手鎚的敘述,下列何者不正確?",
      "image_url": "",
      "options": [
        "使用時應由輕而重施力敲擊",
        "木柄在距頭部三分之一處斷面縮減",
        "木柄斷面縮減的目的是為了方便握持",
        "規格以頭部重量的大小定之"
      ],
      "a": 2,
      "reward": 15,
      "explanation": "(C) 木柄斷面縮減的目的是為減震"
    },
    {
      "id": "MOCK_106_3_ME2_015",
      "subject": "機械群專二",
      "unit": "106-3-四技二專-01機械群專二",
      "q": "有關花崗岩平板與鑄鐵平板比較之敘述,下列何者不正確?",
      "image_url": "",
      "options": [
        "花崗岩平板硬度比鑄鐵平板高",
        "花崗岩平板比鑄鐵平板更耐磨耗",
        "花崗岩平板熱膨脹係數較鑄鐵平板高",
        "花崗岩平板比鑄鐵平板的價格更貴"
      ],
      "a": 2,
      "reward": 15,
      "explanation": "(C) 花崗岩平板熱膨脹係數較鑄鐵平板低"
    },
    {
      "id": "MOCK_106_3_ME2_016",
      "subject": "機械群專二",
      "unit": "106-3-四技二專-01機械群專二",
      "q": "有關銼刀切齒形式中之單切齒的敘述,下列何者正確?",
      "image_url": "",
      "options": [
        "切齒與銼刀邊緣成 40°~45°",
        "適合用於精銼削",
        "常用於皮革銼削",
        "同時具有上切齒及下切齒"
      ],
      "a": 1,
      "reward": 15,
      "explanation": "(A) 切齒與銼刀邊緣成 65°~85° (C) 棘銼齒常用於皮革銼削 (D) 雙銼齒同時具有上切齒及下切齒"
    },
    {
      "id": "MOCK_106_3_ME2_017",
      "subject": "機械群專二",
      "unit": "106-3-四技二專-01機械群專二",
      "q": "銼削時可在銼刀上塗粉筆,下列何者為其主要的功能?",
      "image_url": "",
      "options": [
        "防銹",
        "排屑",
        "省力",
        "吸油"
      ],
      "a": 1,
      "reward": 15,
      "explanation": "正解：(B)；來源：106-3-四技二專-01機械群專二解析.pdf"
    },
    {
      "id": "MOCK_106_3_ME2_018",
      "subject": "機械群專二",
      "unit": "106-3-四技二專-01機械群專二",
      "q": "下列何者不是鋸條折斷的可能原因?",
      "image_url": "",
      "options": [
        "鋸條鋸齒方向朝鋸架後方",
        "鋸條裝於鋸架上夾持太緊",
        "鋸條裝於鋸架上夾持太鬆",
        "使用新鋸條鋸切舊鋸路"
      ],
      "a": 0,
      "reward": 15,
      "explanation": "正解：(A)；來源：106-3-四技二專-01機械群專二解析.pdf"
    },
    {
      "id": "MOCK_106_3_ME2_019",
      "subject": "機械群專二",
      "unit": "106-3-四技二專-01機械群專二",
      "q": "鋸切工作所使用的鋸條,若齒數愈多,則齒距愈小,試問其所適合的工作,下列何者正確?",
      "image_url": "",
      "options": [
        "愈適合大斷面工件的鋸切",
        "愈適合軟材料工件的鋸切",
        "愈適合中空圓薄管工件的鋸切",
        "愈適合塑膠材料工件的鋸切"
      ],
      "a": 2,
      "reward": 15,
      "explanation": "(A) 適合小斷面工件的鋸切 (B) 適合硬材料工件的鋸切 (D) 適合硬質材料工件的鋸切"
    },
    {
      "id": "MOCK_106_3_ME2_020",
      "subject": "機械群專二",
      "unit": "106-3-四技二專-01機械群專二",
      "q": "鑽孔工作中先以高速鋼直徑 6 mm 鑽頭,依刀具材質建議之切削速度選擇使用轉速 1000 rpm,鑽孔後更 換直徑 20 mm 之高速鋼鑽頭,則每分鐘轉速應調整為多少轉?",
      "image_url": "",
      "options": [
        "300 rpm",
        "500 rpm",
        "600 rpm",
        "1000 rpm"
      ],
      "a": 0,
      "reward": 15,
      "explanation": "V    D N ,  6  1000   20  N, N  300 rp m"
    },
    {
      "id": "MOCK_106_3_ME2_021",
      "subject": "機械群專二",
      "unit": "106-3-四技二專-01機械群專二",
      "q": "鉸削時由孔上方往下看,順時針方向為鉸削進刀,則有關鉸削工作時的操作,下列敘述何者正確?",
      "image_url": "",
      "options": [
        "鉸削時順時針旋轉進刀,退刀時逆時針方向旋轉並向下完全通過通孔",
        "鉸削時順時針旋轉進刀,退刀時順時針方向旋轉並向上退出",
        "鉸削時順時針旋轉約一圈半後,逆時針旋轉半圈,直至鉸刀向下通過通孔",
        "鉸削時順時針旋轉進刀,退刀時不可旋轉鉸刀,並直接向上拉出"
      ],
      "a": 1,
      "reward": 15,
      "explanation": "正解：(B)；來源：106-3-四技二專-01機械群專二解析.pdf"
    },
    {
      "id": "MOCK_106_3_ME2_022",
      "subject": "機械群專二",
      "unit": "106-3-四技二專-01機械群專二",
      "q": "下列何者不是鉸孔的目的?",
      "image_url": "",
      "options": [
        "得到正確的孔徑",
        "提高孔的真圓度",
        "改善孔內表面粗糙度",
        "修正圓孔中心偏差"
      ],
      "a": 3,
      "reward": 15,
      "explanation": "正解：(D)；來源：106-3-四技二專-01機械群專二解析.pdf"
    },
    {
      "id": "MOCK_106_3_ME2_023",
      "subject": "機械群專二",
      "unit": "106-3-四技二專-01機械群專二",
      "q": "有關等徑螺絲攻與增徑螺絲攻的敘述,下列何者正確?",
      "image_url": "",
      "options": [
        "等徑螺絲攻一組三支,僅適用於盲孔攻牙",
        "等徑螺絲攻一組三支,三支直徑皆相同,僅前端倒角牙數不同",
        "增徑螺絲攻一組三支,通孔攻牙僅需使用第一攻",
        "增徑螺絲攻一組一支,僅適用於通孔攻牙"
      ],
      "a": 1,
      "reward": 15,
      "explanation": "(A) 等徑螺絲攻一組三支,可用於通孔或盲孔攻牙 (C) 增徑螺絲攻一組三支,通孔攻牙需依序使用三支 螺絲攻 (D) 增徑螺絲攻一組三支,可用於通孔或盲孔攻牙"
    },
    {
      "id": "MOCK_106_3_ME2_024",
      "subject": "機械群專二",
      "unit": "106-3-四技二專-01機械群專二",
      "q": "有關車床工作的敘述,下列何者正確?",
      "image_url": "",
      "options": [
        "三爪聯動夾頭可快速調整好工件的偏心夾持,以供偏心車削工作",
        "車床尾座可裝置內孔車刀,以供車削圓孔內徑",
        "車削工作中遇有鐵屑纏繞,可使用游標卡尺夾除",
        "欲使車床停止時,踩踏剎車踏板可啟動剎車,並可同時切斷電源"
      ],
      "a": 3,
      "reward": 15,
      "explanation": "(A) 三爪聯動夾頭無法車削偏心工件 (B) 車床尾座無法裝置內孔車刀 (C) 車削工作中遇有鐵屑纏繞,應使用鐵屑勾"
    },
    {
      "id": "MOCK_106_3_ME2_025",
      "subject": "機械群專二",
      "unit": "106-3-四技二專-01機械群專二",
      "q": "有關車床刀具角度的敘述,下列何者正確?",
      "image_url": "",
      "options": [
        "陶瓷刀具的前隙角通常採用負值",
        "刀端角愈小,則刀尖與工件接觸長度愈短",
        "後斜角角度愈大,則刀刃愈銳利且刀具壽命愈短",
        "邊斜角的功能是為了避免刀腹與工件摩擦"
      ],
      "a": 2,
      "reward": 15,
      "explanation": "(A) 陶瓷刀具的後斜角通常採用負值"
    },
    {
      "id": "MOCK_106_3_ME2_026",
      "subject": "機械群專二",
      "unit": "106-3-四技二專-01機械群專二",
      "q": "有關車床的操作條件,下列何者最適合精車削工作?",
      "image_url": "",
      "options": [
        "小切削深度,小進給量,高轉速",
        "小切削深度,大進給量,低轉速",
        "大切削深度,大進給量,高轉速",
        "大切削深度,小進給量,低轉速"
      ],
      "a": 0,
      "reward": 15,
      "explanation": "正解：(A)；來源：106-3-四技二專-01機械群專二解析.pdf"
    },
    {
      "id": "MOCK_106_3_ME2_027",
      "subject": "機械群專二",
      "unit": "106-3-四技二專-01機械群專二",
      "q": "有關端面車削操作的敘述,下列何者正確?",
      "image_url": "",
      "options": [
        "端面車削可選用左手外徑刀",
        "端面車削時,由外徑處向工件中心進給時,進給量應愈來愈大",
        "端面中心留一小凸點,原因是車刀刀尖未對準工件中心",
        "工件端面應留到最後再加工,以控制工件長度 第三部分:製圖實習"
      ],
      "a": 2,
      "reward": 15,
      "explanation": "(A) 端面車削通常選用右手外徑刀"
    },
    {
      "id": "MOCK_106_3_ME2_028",
      "subject": "機械群專二",
      "unit": "106-3-四技二專-01機械群專二",
      "q": "裝訂成冊的 A4 圖紙,其左邊的圖框線距離圖紙邊緣為多少 mm?",
      "image_url": "",
      "options": [
        "25 mm",
        "20 mm",
        "15 mm",
        "10 mm"
      ],
      "a": 0,
      "reward": 15,
      "explanation": "(A) 需裝訂成冊的圖, 左邊圖框線應距圖紙邊緣 25 mm"
    },
    {
      "id": "MOCK_106_3_ME2_029",
      "subject": "機械群專二",
      "unit": "106-3-四技二專-01機械群專二",
      "q": "有關「製圖儀器」的敘述,下列何者正確?",
      "image_url": "",
      "options": [
        "量角器可用以畫圓弧",
        "丁字尺可用以畫垂直線",
        "三角板每組兩片",
        "曲線板可用以畫直線"
      ],
      "a": 2,
      "reward": 15,
      "explanation": "正解：(C)；來源：106-3-四技二專-01機械群專二解析.pdf"
    },
    {
      "id": "MOCK_106_3_ME2_030",
      "subject": "機械群專二",
      "unit": "106-3-四技二專-01機械群專二",
      "q": "有關書寫「拉丁字母」的敘述,下列何者不正確?",
      "image_url": "",
      "options": [
        "依 CNS 規範,斜體拉丁字母之傾斜角為 60°",
        "單字之間的間隔以容下一個「 O 」為原則",
        "拉丁字母除特定符號與縮寫以小寫外,都採用大寫書寫 2",
        "行距之間隔約為字高的 3"
      ],
      "a": 0,
      "reward": 15,
      "explanation": "(A) 斜體之傾斜角為 75°"
    },
    {
      "id": "MOCK_106_3_ME2_031",
      "subject": "機械群專二",
      "unit": "106-3-四技二專-01機械群專二",
      "q": "有關「應用幾何」的敘述,下列何者不正確?",
      "image_url": "",
      "options": [
        "兩圓外切時,其連心線長度等於兩半徑之和",
        "在圓周上一點僅能作兩條切線",
        "動點與二定點間之距離和為長軸,其動點軌跡即為橢圓",
        "一圓沿一直線滾動時,圓周上一點之移動軌跡為正擺線"
      ],
      "a": 1,
      "reward": 15,
      "explanation": "(B) 圓周上一點僅能作一條切線 作的溫度在工件的再結晶溫度以下為冷作加工"
    },
    {
      "id": "MOCK_106_3_ME2_032",
      "subject": "機械群專二",
      "unit": "106-3-四技二專-01機械群專二",
      "q": "欲徒手繪製橢圓,下列敘述何者正確?",
      "image_url": "",
      "options": [
        "先繪製橢圓之矩形",
        "先繪製橢圓之圓弧",
        "先繪製橢圓之焦點",
        "先繪製橢圓之長、短軸"
      ],
      "a": 3,
      "reward": 15,
      "explanation": "(D) 徒手繪製橢圓,先繪製長、短軸"
    },
    {
      "id": "MOCK_106_3_ME2_033",
      "subject": "機械群專二",
      "unit": "106-3-四技二專-01機械群專二",
      "q": "如圖 ( 一 ) 所示之投影視圖, 「第三象限」所在位置為何?",
      "image_url": "https://raw.githubusercontent.com/thumb2086/AcademicTycoon_data/main/assets/question_images/exam_106_3_me2/p004_1351_1589_682_998.png",
      "options": [
        "在 HP 之下, VP 之前",
        "在 HP 之下, VP 之後",
        "在 HP 之上, VP 之前",
        "在 HP 之上, VP 之後 圖 ( 一 )"
      ],
      "a": 1,
      "reward": 15,
      "explanation": "(B) 象限分佈如下圖所示"
    },
    {
      "id": "MOCK_106_3_ME2_034",
      "subject": "機械群專二",
      "unit": "106-3-四技二專-01機械群專二",
      "q": "如圖 ( 二 ),已知三視圖中的前視圖和俯視圖,下列何者為正確之右側視圖?",
      "image_url": "https://raw.githubusercontent.com/thumb2086/AcademicTycoon_data/main/assets/question_images/exam_106_3_me2/p005_153_445_638_977.png",
      "options": [
        "",
        "",
        "",
        ""
      ],
      "a": 0,
      "reward": 15,
      "explanation": "正解：(A)；來源：106-3-四技二專-01機械群專二解析.pdf"
    },
    {
      "id": "MOCK_106_3_ME2_035",
      "subject": "機械群專二",
      "unit": "106-3-四技二專-01機械群專二",
      "q": "繪製視圖如遇線條重疊時,以下列何者線條優先繪製? 圖 ( 二 )",
      "image_url": "",
      "options": [
        "割面線",
        "中心線",
        "粗實線",
        "剖面線"
      ],
      "a": 2,
      "reward": 15,
      "explanation": "正解：(C)；來源：106-3-四技二專-01機械群專二解析.pdf"
    },
    {
      "id": "MOCK_106_3_ME2_036",
      "subject": "機械群專二",
      "unit": "106-3-四技二專-01機械群專二",
      "q": "有關「正投影」之敘述,下列何者不正確?",
      "image_url": "",
      "options": [
        "正投影為平行投影",
        "物體離投影面愈遠,視圖愈小",
        "與三個主要投影面之一垂直,與其他兩投影面平行的直線,稱為正垂線",
        "第一角法的右側視圖位於前視圖的左邊"
      ],
      "a": 1,
      "reward": 15,
      "explanation": "正解：(B)；來源：106-3-四技二專-01機械群專二解析.pdf"
    },
    {
      "id": "MOCK_106_3_ME2_037",
      "subject": "機械群專二",
      "unit": "106-3-四技二專-01機械群專二",
      "q": "下列「錐度」之標示,何者不正確?",
      "image_url": "",
      "options": [
        "",
        "",
        "",
        ""
      ],
      "a": 3,
      "reward": 15,
      "explanation": "正解：(D)；來源：106-3-四技二專-01機械群專二解析.pdf"
    },
    {
      "id": "MOCK_106_3_ME2_038",
      "subject": "機械群專二",
      "unit": "106-3-四技二專-01機械群專二",
      "q": "下列「旋轉剖面」畫法,何者正確?",
      "image_url": "",
      "options": [
        "",
        "",
        "",
        ""
      ],
      "a": 2,
      "reward": 15,
      "explanation": "正解：(C)；來源：106-3-四技二專-01機械群專二解析.pdf"
    },
    {
      "id": "MOCK_106_3_ME2_039",
      "subject": "機械群專二",
      "unit": "106-3-四技二專-01機械群專二",
      "q": "有關「剖面線」之敘述,下列何者不正確?",
      "image_url": "",
      "options": [
        "剖面線不一定與水平成 45°",
        "大型構件繪製剖視圖時,剖面線應將中間省略不繪,僅需在輪廓邊緣整齊繪製",
        "薄墊圈繪製剖面時,可以塗黑方式繪製",
        "兩相鄰物件之組合圖,其剖面線方向及間隔應一致"
      ],
      "a": 3,
      "reward": 15,
      "explanation": "正解：(D)；來源：106-3-四技二專-01機械群專二解析.pdf"
    },
    {
      "id": "MOCK_106_3_ME2_040",
      "subject": "機械群專二",
      "unit": "106-3-四技二專-01機械群專二",
      "q": "下列敘述何者不正確?",
      "image_url": "",
      "options": [
        "表面特殊處理的範圍線用細鏈線表示",
        "繪製未剖視之半視圖時,所繪之半視圖為與剖視圖對應之鄰近視圖",
        "局部視圖可平移至圖面任何位置",
        "圓柱表面削平部分,在矩形範圍內畫對角交叉細實線表示 【以下空白】"
      ],
      "a": 0,
      "reward": 15,
      "explanation": "(A) 表面特殊處理範圍線用粗鏈線表示 第三部分:製圖實習"
    }
  ]
}
